datacake/__init__.py
datacake/core.py
datacake-1.0.2.dist-info/LICENSE
datacake-1.0.2.dist-info/METADATA
datacake-1.0.2.dist-info/WHEEL
datacake-1.0.2.dist-info/top_level.txt
datacake-1.0.2.dist-info/RECORD
