Metadata-Version: 2.1
Name: datacake
Version: 1.0.2
Summary: Utility library for data analysis.
Author-email: Sintrias <j3f9y.f@gmail.com>
Classifier: Programming Language :: Python :: 3
Classifier: License :: OSI Approved :: MIT License
Classifier: Operating System :: OS Independent
Requires-Python: >=3.10
License-File: LICENSE
